README.rst
setup.py
buscacep/__init__.py
buscacep.egg-info/PKG-INFO
buscacep.egg-info/SOURCES.txt
buscacep.egg-info/dependency_links.txt
buscacep.egg-info/requires.txt
buscacep.egg-info/top_level.txt