Metadata-Version: 1.1
Name: buscacep
Version: 0.1.1
Summary: Biblioteca utilitária para a utilização do serviço de busca de CEPs disponibilizado no website do Correio
Home-page: https://github.com/fabito/buscacep-python-client
Author: Fábio Franco Uechi
Author-email: fabio.uechi@gmail.com
License: MIT
Keywords: cep brasil busca
Platform: UNKNOWN
Classifier: Development Status :: 4 - Beta
Classifier: Intended Audience :: Developers
Classifier: Topic :: Software Development :: Build Tools
Classifier: License :: OSI Approved :: MIT License
Classifier: Programming Language :: Python :: 2
Classifier: Programming Language :: Python :: 2.6
Classifier: Programming Language :: Python :: 2.7
Classifier: Programming Language :: Python :: 3
Classifier: Programming Language :: Python :: 3.2
Classifier: Programming Language :: Python :: 3.3
Classifier: Programming Language :: Python :: 3.4
